pyarmor/cli/__init__.py
pyarmor/cli/__main__.py
pyarmor/cli/batch.py
pyarmor/cli/bootstrap.py
pyarmor/cli/bug.py
pyarmor/cli/command.py
pyarmor/cli/config.py
pyarmor/cli/context.py
pyarmor/cli/core.data.1
pyarmor/cli/core.data.2
pyarmor/cli/core.data.3
pyarmor/cli/default.cfg
pyarmor/cli/docker.py
pyarmor/cli/generate.py
pyarmor/cli/hdinfo.py
pyarmor/cli/merge.py
pyarmor/cli/mixer.py
pyarmor/cli/model.py
pyarmor/cli/plugin.py
pyarmor/cli/project.py
pyarmor/cli/public_capsule.zip
pyarmor/cli/register.py
pyarmor/cli/repack.py
pyarmor/cli/resource.py
pyarmor/cli/shell.py
pyarmor_cli-9.2.3.dist-info/METADATA
pyarmor_cli-9.2.3.dist-info/WHEEL
pyarmor_cli-9.2.3.dist-info/entry_points.txt
pyarmor_cli-9.2.3.dist-info/top_level.txt
pyarmor_cli-9.2.3.dist-info/RECORD
