Metadata-Version: 2.1
Name: pyarmor.cli
Version: 9.2.3
Summary: A comand line tool to obfuscate python scripts
Home-page: https://github.com/dashingsoft/pyarmor
Author: Jondy Zhao
Author-email: pyarmor@163.com
License: Free To Use But Restricted
Keywords: protect obfuscate encrypt obfuscation distribute
Classifier: Programming Language :: Python :: 3
Classifier: License :: Free To Use But Restricted
Classifier: Operating System :: MacOS
Classifier: Operating System :: Microsoft :: Windows
Classifier: Operating System :: POSIX
Classifier: Intended Audience :: Developers
Classifier: Topic :: Software Development :: Build Tools
Classifier: Topic :: Utilities
Classifier: Topic :: Security
Classifier: Topic :: System :: Software Distribution
Requires-Dist: pyarmor.cli.core ~=8.1.0
